Metadata-Version: 2.1
Name: B-FeelLog
Version: 1.0.1
Summary: free source minimal multilingual blog maker and manager for different blog entries and multiple blog entries , with web interface. in this blog can use images but we looking to keep it minimalism.
Home-page: https://jero98772.pythonanywhere.com/
Author: jero98772
Author-email: jero98772@protonmail.com
License: GPLv3
Platform: UNKNOWN
License-File: LICENSE
